<?xml version="1.0" encoding="UTF-8"?>
<objects serializationModel="Studio.02.02.00">
	<object class="AudioFile" id="{533d5de7-1dbc-4556-80e3-80c2730dcdfe}">
		<property name="assetPath">
			<value>Dialog/Announcer/av_pc_Announcer_D4_Start.wav</value>
		</property>
		<property name="frequencyInKHz">
			<value>48</value>
		</property>
		<property name="channelCount">
			<value>2</value>
		</property>
		<property name="length">
			<value>8.7248958333333331</value>
		</property>
		<relationship name="masterAssetFolder">
			<destination>{f28a448e-210f-4343-bfe1-39a1756b5fe2}</destination>
		</relationship>
	</object>
</objects>
